{
  "version": 3,
  "middleware": {
    "/": {
      "files": [
        "server/edge-runtime-webpack.js",
        "server/middleware.js"
      ],
      "name": "middleware",
      "page": "/",
      "matchers": [
        {
          "regexp": "^(?:\\/(_next\\/data\\/[^/]{1,}))?(?:\\/((?!_next\\/static|_next\\/image|favicon.ico|.*\\.(?:svg|png|jpg|jpeg|gif|webp)$).*))(\\.json)?[\\/#\\?]?$",
          "originalSource": "/((?!_next/static|_next/image|favicon.ico|.*\\.(?:svg|png|jpg|jpeg|gif|webp)$).*)"
        }
      ],
      "wasm": [],
      "assets": [],
      "env": {
        "__NEXT_BUILD_ID": "seoPx_O0_xDRILfxMQmkN",
        "NEXT_SERVER_ACTIONS_ENCRYPTION_KEY": "0OUqCX4/nc7jN09SqOrU/4pnFY7PVI4dQLPAFTh4cjY=",
        "__NEXT_PREVIEW_MODE_ID": "09d09c2f3e22dc2d83aecee547c73e91",
        "__NEXT_PREVIEW_MODE_ENCRYPTION_KEY": "a5345cf20524209a796a962f3e16103270754009e3ee5bb4affd72ab3459f910",
        "__NEXT_PREVIEW_MODE_SIGNING_KEY": "2e0e9813de39d58e6a1b68d6bdb263dc58d54fbd855137db30c25cf135bb0639"
      }
    }
  },
  "functions": {},
  "sortedMiddleware": [
    "/"
  ]
}